moat/link/notify/__init__.py
moat/link/notify/_cfg.yaml
moat/link/notify/_main.py
moat/link/notify/ntfy.py
moat_link_notify-0.0.1.dist-info/licenses/LICENSE.txt
moat_link_notify-0.0.1.dist-info/METADATA
moat_link_notify-0.0.1.dist-info/WHEEL
moat_link_notify-0.0.1.dist-info/top_level.txt
moat_link_notify-0.0.1.dist-info/RECORD
