Metadata-Version: 2.4
Name: moat-link-notify
Version: 0.0.1
Summary: Notification gateway for MoaT-Link
Author-email: Matthias Urlichs <matthias@urlichs.de>
Project-URL: homepage, https://m-o-a-t.org
Project-URL: repository, https://github.com/M-o-a-T/moat
Keywords: MoaT
Classifier: Intended Audience :: Developers
Classifier: Programming Language :: Python :: 3
Classifier: Framework :: AsyncIO
Classifier: Framework :: Trio
Classifier: Framework :: AnyIO
Classifier: Development Status :: 4 - Beta
Requires-Python: >=3.8
License-File: LICENSE.txt
Requires-Dist: anyio~=4.2
Requires-Dist: asyncclick
Requires-Dist: attrs
Requires-Dist: httpx
Requires-Dist: moat-util~=0.62.2
Requires-Dist: moat-link~=0.2.46
Dynamic: license-file
